whisperl-0.2.17.dist-info/licenses/LICENSE
whisperlivekit/__init__.py
whisperlivekit/audio_processor.py
whisperlivekit/backend_support.py
whisperlivekit/basic_server.py
whisperlivekit/core.py
whisperlivekit/ffmpeg_manager.py
whisperlivekit/model_paths.py
whisperlivekit/parse_args.py
whisperlivekit/silero_vad_iterator.py
whisperlivekit/timed_objects.py
whisperlivekit/tokens_alignment.py
whisperlivekit/warmup.py
whisperlivekit/diarization/__init__.py
whisperlivekit/diarization/diart_backend.py
whisperlivekit/diarization/sortformer_backend.py
whisperlivekit/local_agreement/__init__.py
whisperlivekit/local_agreement/backends.py
whisperlivekit/local_agreement/online_asr.py
whisperlivekit/local_agreement/whisper_online.py
whisperlivekit/silero_vad_models/__init__.py
whisperlivekit/silero_vad_models/silero_vad.jit
whisperlivekit/silero_vad_models/silero_vad.onnx
whisperlivekit/silero_vad_models/silero_vad_16k_op15.onnx
whisperlivekit/silero_vad_models/silero_vad_half.onnx
whisperlivekit/simul_whisper/__init__.py
whisperlivekit/simul_whisper/backend.py
whisperlivekit/simul_whisper/beam.py
whisperlivekit/simul_whisper/config.py
whisperlivekit/simul_whisper/decoder_state.py
whisperlivekit/simul_whisper/eow_detection.py
whisperlivekit/simul_whisper/mlx_encoder.py
whisperlivekit/simul_whisper/simul_whisper.py
whisperlivekit/simul_whisper/token_buffer.py
whisperlivekit/web/__init__.py
whisperlivekit/web/live_transcription.css
whisperlivekit/web/live_transcription.html
whisperlivekit/web/live_transcription.js
whisperlivekit/web/pcm_worklet.js
whisperlivekit/web/recorder_worker.js
whisperlivekit/web/web_interface.py
whisperlivekit/web/src/dark_mode.svg
whisperlivekit/web/src/language.svg
whisperlivekit/web/src/light_mode.svg
whisperlivekit/web/src/settings.svg
whisperlivekit/web/src/silence.svg
whisperlivekit/web/src/speaker.svg
whisperlivekit/web/src/system_mode.svg
whisperlivekit/web/src/translate.svg
whisperlivekit/whisper/__init__.py
whisperlivekit/whisper/__main__.py
whisperlivekit/whisper/audio.py
whisperl-0.2.17.dist-info/METADATA
whisperl-0.2.17.dist-info/WHEEL
whisperl-0.2.17.dist-info/entry_points.txt
whisperl-0.2.17.dist-info/top_level.txt
whisperl-0.2.17.dist-info/RECORD
